dmart/__init__.py
dmart/alembic.ini
dmart/bundler.py
dmart/cli.py
dmart/config.env.sample
dmart/config.ini.sample
dmart/conftest.py
dmart/curl.pypi.sh
dmart/curl.sh
dmart/data_generator.py
dmart/dmart.py
dmart/get_settings.py
dmart/hypercorn_config.toml
dmart/info.json
dmart/login_creds.sh
dmart/login_creds.sh.sample
dmart/main.py
dmart/manifest.sh
dmart/migrate.py
dmart/password_gen.py
dmart/publish.sh
dmart/pylint.sh
dmart/pyrightconfig.json
dmart/redis_connections.sh
dmart/reload.sh
dmart/run.sh
dmart/run_notification_campaign.py
dmart/scheduled_notification_handler.py
dmart/schema_migration.py
dmart/schema_modulate.py
dmart/set_admin_passwd.py
dmart/sync.py
dmart/test_utils.py
dmart/websocket.py
dmart/alembic/README
dmart/alembic/__init__.py
dmart/alembic/env.py
dmart/alembic/notes.txt
dmart/alembic/script.py.mako
dmart/alembic/scripts/__init__.py
dmart/alembic/scripts/calculate_checksums.py
dmart/alembic/scripts/migration_f7a4949eed19.py
dmart/alembic/versions/0f3d2b1a7c21_add_authz_materialized_views.py
dmart/alembic/versions/10d2041b94d4_last_checksum_history.py
dmart/alembic/versions/1cf4e1ee3cb8_ext_permission_with_filter_fields_values.py
dmart/alembic/versions/26bfe19b49d4_rm_failedloginattempts.py
dmart/alembic/versions/3c8bca2219cc_add_otp_table.py
dmart/alembic/versions/6675fd9dfe42_remove_unique_from_sessions_table.py
dmart/alembic/versions/71bc1df82e6a_adding_user_last_login_at.py
dmart/alembic/versions/74288ccbd3b5_initial.py
dmart/alembic/versions/7520a89a8467_rm_activesession_table.py
dmart/alembic/versions/848b623755a4_make_created_nd_updated_at_required.py
dmart/alembic/versions/8640dcbebf85_add_notes_to_users.py
dmart/alembic/versions/91c94250232a_adding_fk_on_owner_shortname.py
dmart/alembic/versions/98ecd6f56f9a_ext_meta_with_owner_group_shortname.py
dmart/alembic/versions/9aae9138c4ef_indexing_created_at_updated_at.py
dmart/alembic/versions/__init__.py
dmart/alembic/versions/b53f916b3f6d_json_to_jsonb.py
dmart-1.4.41.post35.dist-info/METADATA
dmart-1.4.41.post35.dist-info/WHEEL
dmart-1.4.41.post35.dist-info/entry_points.txt
dmart-1.4.41.post35.dist-info/top_level.txt
dmart-1.4.41.post35.dist-info/RECORD
