Metadata-Version: 2.4
Name: dmart
Version: 1.4.41.post35
Requires-Python: >=3.11
Requires-Dist: fastapi
Requires-Dist: pydantic
Requires-Dist: pydantic[email]
Requires-Dist: concurrent-log-handler
Requires-Dist: hypercorn
Requires-Dist: pyjwt
Requires-Dist: redis
Requires-Dist: aiofiles
Requires-Dist: aiohttp
Requires-Dist: python-multipart
Requires-Dist: jsonschema
Requires-Dist: email-validator
Requires-Dist: asgi-correlation-id
Requires-Dist: pydantic-settings
Requires-Dist: fastapi-sso
Requires-Dist: sqlmodel
Requires-Dist: psycopg[binary]
Requires-Dist: greenlet
Requires-Dist: alembic
Requires-Dist: jinja2
Requires-Dist: pytest-cov
Requires-Dist: argon2-cffi
Requires-Dist: orjson
Requires-Dist: prompt_toolkit
Requires-Dist: rich
Requires-Dist: requests
Requires-Dist: alembic
Dynamic: requires-dist
Dynamic: requires-python
